basenef/__init__.py
basenef/arithematic_ops.py
basenef/base.py
basenef/config.py
basenef/typings.py
basenef/utils.py
basenef/version.py
basenef/mixin/__init__.py
basenef/mixin/arithematic_ops.py
basenef/mixin/image_related.py
basenef/tools/__init__.py
basenef/tools/api/__init__.py
basenef/tools/api/class_schema_parser.py
basenef/tools/api/instance_dict_parser.py
basenef/tools/api/json.py
basenef/tools/doc_gen/__init__.py
basenef/tools/doc_gen/cli.py
basenef/tools/doc_gen/doc_generator.py
basenef/tools/doc_gen/figure_generator.py
basenef/tools/file_io/__init__.py
basenef/tools/file_io/file_io.py
basenef/tools/file_io/sftp.py
basenef-0.1.2.3.1555428104.dist-info/LICENSE
basenef-0.1.2.3.1555428104.dist-info/METADATA
basenef-0.1.2.3.1555428104.dist-info/WHEEL
basenef-0.1.2.3.1555428104.dist-info/entry_points.txt
basenef-0.1.2.3.1555428104.dist-info/top_level.txt
basenef-0.1.2.3.1555428104.dist-info/RECORD
