Metadata-Version: 2.1
Name: basenef
Version: 0.1.2.3.1555428104
Summary: Not Enough Functions basing module
Home-page: UNKNOWN
Author: Minghao Guo
Author-email: mh.guo0111@gmail.com
License: Apache
Platform: UNKNOWN
Requires-Dist: scipy
Requires-Dist: matplotlib
Requires-Dist: typing
Requires-Dist: h5py
Requires-Dist: click
Requires-Dist: numpy
Requires-Dist: tqdm
Requires-Dist: numba
Requires-Dist: deepdish (==0.3.6)
Requires-Dist: Click
